[{"created_at":"2020-06-17T10:36:50Z","url":"https://github.com/teamdigitale/anpr-dashboard/issues/39","title":"External cdn libraries should be local and managed by package.json","name":"anpr-dashboard","language":[],"repository_url":"https://github.com/teamdigitale/anpr-dashboard","labels":["enhancement"],"type":"enhancement","subproject":"anpr-dashboard","project":"anpr"},{"created_at":"2019-12-18T17:54:29Z","url":"https://github.com/teamdigitale/confini-amministrativi-istat/issues/14","title":"JSON annidato delle divisioni amministrative","name":"confini-amministrativi-istat","language":[],"repository_url":"https://github.com/teamdigitale/confini-amministrativi-istat","labels":["enhancement","good first issue"],"type":"enhancement","subproject":"confini-amministrativi-istat","project":"other"},{"created_at":"2019-12-05T14:43:53Z","url":"https://github.com/teamdigitale/confini-amministrativi-istat/issues/10","title":"Formati spaziali: shp e geopackage","name":"confini-amministrativi-istat","language":[],"repository_url":"https://github.com/teamdigitale/confini-amministrativi-istat","labels":["enhancement","question"],"type":"enhancement","subproject":"confini-amministrativi-istat","project":"other"},{"created_at":"2019-12-05T09:05:21Z","url":"https://github.com/teamdigitale/confini-amministrativi-istat/issues/8","title":"Aggiungere le informazioni sulle divisioni amministrative anche a tutte le altre risorse ISTAT nel file `sources.json`.","name":"confini-amministrativi-istat","language":[],"repository_url":"https://github.com/teamdigitale/confini-amministrativi-istat","labels":["enhancement","good first issue"],"type":"enhancement","subproject":"confini-amministrativi-istat","project":"other"},{"created_at":"2019-12-05T09:02:11Z","url":"https://github.com/teamdigitale/confini-amministrativi-istat/issues/7","title":"Fix della conversione del geojson in geobuf.","name":"confini-amministrativi-istat","language":[],"repository_url":"https://github.com/teamdigitale/confini-amministrativi-istat","labels":["bug"],"type":"bug","subproject":"confini-amministrativi-istat","project":"other"},{"created_at":"2019-12-05T08:56:55Z","url":"https://github.com/teamdigitale/confini-amministrativi-istat/issues/6","title":"Verifica della qualità e della completezza del formato geojson rispetto agli shapefile originali.","name":"confini-amministrativi-istat","language":[],"repository_url":"https://github.com/teamdigitale/confini-amministrativi-istat","labels":["good first issue"],"type":"","subproject":"confini-amministrativi-istat","project":"other"},{"created_at":"2019-12-05T08:55:53Z","url":"https://github.com/teamdigitale/confini-amministrativi-istat/issues/5","title":"Verifica della qualità e della completezza del formato topojson rispetto agli shapefile originali.","name":"confini-amministrativi-istat","language":[],"repository_url":"https://github.com/teamdigitale/confini-amministrativi-istat","labels":["bug","good first issue"],"type":"bug","subproject":"confini-amministrativi-istat","project":"other"},{"created_at":"2020-08-20T14:53:32Z","url":"https://github.com/teamdigitale/api-oas-checker/issues/52","title":"Stop validation asap if tab `\\t` is present","name":"api-oas-checker","language":[],"repository_url":"https://github.com/teamdigitale/api-oas-checker","labels":[],"type":"Hacktoberfest","subproject":"api-oas-checker","project":"other"},{"created_at":"2020-06-16T12:56:32Z","url":"https://github.com/teamdigitale/api-oas-checker/issues/26","title":"Selectively disable spectral rules","name":"api-oas-checker","language":[],"repository_url":"https://github.com/teamdigitale/api-oas-checker","labels":[],"type":"Hacktoberfest","subproject":"api-oas-checker","project":"other"},{"created_at":"2020-04-06T10:24:22Z","url":"https://github.com/teamdigitale/api-oas-checker/issues/5","title":"Fix non-https retrieval of http://json-schema.org/draft-04/schema","name":"api-oas-checker","language":[],"repository_url":"https://github.com/teamdigitale/api-oas-checker","labels":[],"type":"Hacktoberfest","subproject":"api-oas-checker","project":"other"},{"created_at":"2020-04-06T08:20:17Z","url":"https://github.com/teamdigitale/api-oas-checker/issues/4","title":"Improve the bootstrap interface","name":"api-oas-checker","language":[],"repository_url":"https://github.com/teamdigitale/api-oas-checker","labels":[],"type":"Hacktoberfest","subproject":"api-oas-checker","project":"other"},{"created_at":"2020-03-03T10:26:58Z","url":"https://github.com/teamdigitale/api-oas-checker/issues/2","title":"Warn about OAS spec too long","name":"api-oas-checker","language":[],"repository_url":"https://github.com/teamdigitale/api-oas-checker","labels":[],"type":"Hacktoberfest","subproject":"api-oas-checker","project":"other"},{"created_at":"2017-12-30T22:48:01Z","url":"https://github.com/italia/design-web-toolkit/issues/126","title":"rendering templates via php?","name":"design-web-toolkit","language":["design"],"repository_url":"https://github.com/italia/design-web-toolkit","labels":[],"type":"","subproject":"design-web-toolkit","project":"design"},{"created_at":"2017-09-26T14:12:43Z","url":"https://github.com/italia/design-web-toolkit/issues/100","title":"Crea un template per un'ipotetica interfaccia di amministrazione","name":"design-web-toolkit","language":["design"],"repository_url":"https://github.com/italia/design-web-toolkit","labels":[],"type":"","subproject":"design-web-toolkit","project":"design"},{"created_at":"2017-03-27T10:32:27Z","url":"https://github.com/italia/design-web-toolkit/issues/67","title":"toggle buttons","name":"design-web-toolkit","language":["design"],"repository_url":"https://github.com/italia/design-web-toolkit","labels":["enhancement","priorita:bassa"],"type":"enhancement","subproject":"design-web-toolkit","project":"design"},{"created_at":"2016-12-29T11:18:16Z","url":"https://github.com/italia/design-web-toolkit/issues/46","title":"integrazione test suite","name":"design-web-toolkit","language":["design"],"repository_url":"https://github.com/italia/design-web-toolkit","labels":["nuova funzionalità","priorita:normale"],"type":"","subproject":"design-web-toolkit","project":"design"},{"created_at":"2016-12-16T14:06:47Z","url":"https://github.com/italia/design-web-toolkit/issues/43","title":"possibilità di utilizzare il toolkit come dipendenza npm","name":"design-web-toolkit","language":["design"],"repository_url":"https://github.com/italia/design-web-toolkit","labels":["enhancement","priorita:bassa"],"type":"enhancement","subproject":"design-web-toolkit","project":"design"},{"created_at":"2016-12-16T13:59:02Z","url":"https://github.com/italia/design-web-toolkit/issues/41","title":"indicatori di progresso per form multistep","name":"design-web-toolkit","language":["design"],"repository_url":"https://github.com/italia/design-web-toolkit","labels":["design pattern","priorita:normale"],"type":"","subproject":"design-web-toolkit","project":"design"},{"created_at":"2016-10-21T10:19:23Z","url":"https://github.com/italia/design-web-toolkit/issues/23","title":"calendario / agenda","name":"design-web-toolkit","language":["design"],"repository_url":"https://github.com/italia/design-web-toolkit","labels":["enhancement","nuovo componente"],"type":"enhancement","subproject":"design-web-toolkit","project":"design"},{"created_at":"2016-10-10T08:35:03Z","url":"https://github.com/italia/design-web-toolkit/issues/8","title":"Interfaccia per build custom","name":"design-web-toolkit","language":["design"],"repository_url":"https://github.com/italia/design-web-toolkit","labels":["enhancement","nuova funzionalità","priorita:normale"],"type":"enhancement","subproject":"design-web-toolkit","project":"design"},{"created_at":"2016-10-10T08:33:22Z","url":"https://github.com/italia/design-web-toolkit/issues/7","title":"Nuovo componente: Mappa interattiva","name":"design-web-toolkit","language":["design"],"repository_url":"https://github.com/italia/design-web-toolkit","labels":["enhancement","nuovo componente","priorita:normale"],"type":"enhancement","subproject":"design-web-toolkit","project":"design"},{"created_at":"2017-09-21T17:31:11Z","url":"https://github.com/italia/anpr/issues/314","title":"Piattaforma di analytics delle issue github","name":"anpr","language":[],"repository_url":"https://github.com/italia/anpr","labels":["new project","no-SLO"],"type":"new project","subproject":"anpr","project":"other"},{"created_at":"2017-09-21T17:22:52Z","url":"https://github.com/italia/anpr/issues/313","title":"Piattaforma di ricerca e rimozione di informazioni personali da issue github","name":"anpr","language":[],"repository_url":"https://github.com/italia/anpr","labels":["new project","no-SLO"],"type":"new project","subproject":"anpr","project":"other"},{"created_at":"2017-09-21T17:11:51Z","url":"https://github.com/italia/anpr/issues/311","title":"Generatore di documentazione HTML navigabile a partire dai WSDL","name":"anpr","language":[],"repository_url":"https://github.com/italia/anpr","labels":["new project","no-SLO"],"type":"new project","subproject":"anpr","project":"other"},{"created_at":"2020-09-14T10:07:03Z","url":"https://github.com/italia/developers.italia.it/issues/692","title":"Use the resized image in avatars from GitHub","name":"developers.italia.it","language":[],"repository_url":"https://github.com/italia/developers.italia.it","labels":["enhancement","good-first-issue"],"type":"Hacktoberfest","subproject":"developers.italia.it","project":"website"},{"created_at":"2020-09-12T17:12:25Z","url":"https://github.com/italia/developers.italia.it/issues/688","title":"\"Community leaders\" Does not have \"Dot\" Pagination. ","name":"developers.italia.it","language":[],"repository_url":"https://github.com/italia/developers.italia.it","labels":["bug","good-first-issue"],"type":"Hacktoberfest","subproject":"developers.italia.it","project":"website"},{"created_at":"2020-09-11T08:52:20Z","url":"https://github.com/italia/developers.italia.it/issues/682","title":"API are filtered in search modal but not in search page","name":"developers.italia.it","language":[],"repository_url":"https://github.com/italia/developers.italia.it","labels":["API","bug","triage"],"type":"Hacktoberfest","subproject":"developers.italia.it","project":"website"},{"created_at":"2020-09-11T08:39:16Z","url":"https://github.com/italia/developers.italia.it/issues/678","title":"API pages marked as \"coming soon\" should not be indexed","name":"developers.italia.it","language":[],"repository_url":"https://github.com/italia/developers.italia.it","labels":["API","bug","good-first-issue"],"type":"Hacktoberfest","subproject":"developers.italia.it","project":"website"},{"created_at":"2020-09-11T08:22:48Z","url":"https://github.com/italia/developers.italia.it/issues/677","title":"script/github_importer.rb could probably benefit from using GraphQL","name":"developers.italia.it","language":[],"repository_url":"https://github.com/italia/developers.italia.it","labels":["enhancement","good-first-issue"],"type":"Hacktoberfest","subproject":"developers.italia.it","project":"website"},{"created_at":"2020-09-10T08:52:21Z","url":"https://github.com/italia/developers.italia.it/issues/672","title":"Search modal: \"Misc\" category does not have an icon","name":"developers.italia.it","language":[],"repository_url":"https://github.com/italia/developers.italia.it","labels":["enhancement","frontend","good-first-issue","triage"],"type":"Hacktoberfest","subproject":"developers.italia.it","project":"website"},{"created_at":"2020-08-12T14:15:06Z","url":"https://github.com/italia/developers.italia.it/issues/623","title":"Switch to Jekyll 4.x","name":"developers.italia.it","language":[],"repository_url":"https://github.com/italia/developers.italia.it","labels":["enhancement","triage"],"type":"Hacktoberfest","subproject":"developers.italia.it","project":"website"},{"created_at":"2020-07-02T07:48:06Z","url":"https://github.com/italia/developers.italia.it/issues/600","title":"Translate FAQ in English","name":"developers.italia.it","language":[],"repository_url":"https://github.com/italia/developers.italia.it","labels":["feature-request"],"type":"Hacktoberfest","subproject":"developers.italia.it","project":"website"},{"created_at":"2020-01-27T18:27:39Z","url":"https://github.com/italia/developers.italia.it/issues/491","title":"Tagline/agenda of Developers Italia also getting selected if hovered over the logo.","name":"developers.italia.it","language":[],"repository_url":"https://github.com/italia/developers.italia.it","labels":["frontend","good-first-issue","triage"],"type":"","subproject":"developers.italia.it","project":"website"},{"created_at":"2019-10-08T08:24:04Z","url":"https://github.com/italia/developers.italia.it/issues/431","title":"Consider inserting an icon to denote external links","name":"developers.italia.it","language":[],"repository_url":"https://github.com/italia/developers.italia.it","labels":["enhancement","frontend","good-first-issue"],"type":"enhancement","subproject":"developers.italia.it","project":"website"},{"created_at":"2019-06-27T08:45:23Z","url":"https://github.com/italia/developers.italia.it/issues/345","title":"Translate pages in English","name":"developers.italia.it","language":[],"repository_url":"https://github.com/italia/developers.italia.it","labels":["frontend","good-first-issue"],"type":"Hacktoberfest","subproject":"developers.italia.it","project":"website"},{"created_at":"2017-11-16T11:00:47Z","url":"https://github.com/italia/spid-ansible-shibboleth-example/issues/25","title":"Playbook per Shibboleth","name":"spid-ansible-shibboleth-example","language":["ansible","docker"],"repository_url":"https://github.com/italia/spid-ansible-shibboleth-example","labels":[],"type":"","subproject":"spid-ansible-shibboleth-example","project":"spid"},{"created_at":"2017-10-03T15:25:21Z","url":"https://github.com/italia/spid-ansible-shibboleth-example/issues/23","title":"Documentare installazione manuale Shibboleth","name":"spid-ansible-shibboleth-example","language":["ansible","docker"],"repository_url":"https://github.com/italia/spid-ansible-shibboleth-example","labels":["documentation","enhancement"],"type":"enhancement","subproject":"spid-ansible-shibboleth-example","project":"spid"},{"created_at":"2017-09-24T10:36:03Z","url":"https://github.com/italia/spid-ansible-shibboleth-example/issues/22","title":"Attributi Format e NameQualifier nella Logout Request","name":"spid-ansible-shibboleth-example","language":["ansible","docker"],"repository_url":"https://github.com/italia/spid-ansible-shibboleth-example","labels":["bug"],"type":"bug","subproject":"spid-ansible-shibboleth-example","project":"spid"},{"created_at":"2017-04-05T19:19:01Z","url":"https://github.com/italia/spid-ansible-shibboleth-example/issues/12","title":"Verificare che la configurazione anti-spoofing sia completa e funzionante","name":"spid-ansible-shibboleth-example","language":["ansible","docker"],"repository_url":"https://github.com/italia/spid-ansible-shibboleth-example","labels":[],"type":"","subproject":"spid-ansible-shibboleth-example","project":"spid"},{"created_at":"2017-03-29T06:16:12Z","url":"https://github.com/italia/spid-ansible-shibboleth-example/issues/9","title":"Supporto configurazione StorageService","name":"spid-ansible-shibboleth-example","language":["ansible","docker"],"repository_url":"https://github.com/italia/spid-ansible-shibboleth-example","labels":["enhancement"],"type":"enhancement","subproject":"spid-ansible-shibboleth-example","project":"spid"},{"created_at":"2017-03-28T11:07:33Z","url":"https://github.com/italia/spid-ansible-shibboleth-example/issues/5","title":"Supportare altre distribuzioni Linux","name":"spid-ansible-shibboleth-example","language":["ansible","docker"],"repository_url":"https://github.com/italia/spid-ansible-shibboleth-example","labels":["enhancement"],"type":"enhancement","subproject":"spid-ansible-shibboleth-example","project":"spid"},{"created_at":"2017-03-28T11:03:23Z","url":"https://github.com/italia/spid-ansible-shibboleth-example/issues/4","title":"Esporre CSS Shibboleth","name":"spid-ansible-shibboleth-example","language":["ansible","docker"],"repository_url":"https://github.com/italia/spid-ansible-shibboleth-example","labels":["enhancement"],"type":"enhancement","subproject":"spid-ansible-shibboleth-example","project":"spid"},{"created_at":"2017-03-28T11:01:22Z","url":"https://github.com/italia/spid-ansible-shibboleth-example/issues/3","title":"Pagina login di esempio","name":"spid-ansible-shibboleth-example","language":["ansible","docker"],"repository_url":"https://github.com/italia/spid-ansible-shibboleth-example","labels":[],"type":"","subproject":"spid-ansible-shibboleth-example","project":"spid"},{"created_at":"2017-03-28T10:54:01Z","url":"https://github.com/italia/spid-ansible-shibboleth-example/issues/2","title":"Integrare nginx-letsencrypt con shibboleth-nginx","name":"spid-ansible-shibboleth-example","language":["ansible","docker"],"repository_url":"https://github.com/italia/spid-ansible-shibboleth-example","labels":["enhancement"],"type":"enhancement","subproject":"spid-ansible-shibboleth-example","project":"spid"},{"created_at":"2018-02-21T10:54:58Z","url":"https://github.com/italia/cie-middleware/issues/56","title":"Documentazione per sviluppatori","name":"cie-middleware","language":["cpp"],"repository_url":"https://github.com/italia/cie-middleware","labels":["docs"],"type":"","subproject":"cie-middleware","project":"cie"},{"created_at":"2017-09-26T13:18:49Z","url":"https://github.com/italia/cie-middleware/issues/20","title":"Refactoring per localizzazione messaggi","name":"cie-middleware","language":["cpp"],"repository_url":"https://github.com/italia/cie-middleware","labels":["enhancement"],"type":"enhancement","subproject":"cie-middleware","project":"cie"},{"created_at":"2017-10-06T15:34:28Z","url":"https://github.com/italia/daf/issues/144","title":"Integrazione di GovPay con il Data & Analytics Framework (DAF)","name":"daf","language":[],"repository_url":"https://github.com/italia/daf","labels":["new project"],"type":"new project","subproject":"daf","project":"other"},{"created_at":"2017-10-06T13:58:44Z","url":"https://github.com/italia/daf/issues/143","title":"Add Continuous Integration check to this and other DAF repositories","name":"daf","language":[],"repository_url":"https://github.com/italia/daf","labels":["enhancement"],"type":"enhancement","subproject":"daf","project":"other"},{"created_at":"2017-12-20T11:04:47Z","url":"https://github.com/italia/cie-ideaapp/issues/10","title":"Verifica di autenticità","name":"cie-ideaapp","language":["java","android"],"repository_url":"https://github.com/italia/cie-ideaapp","labels":["enhancement","question"],"type":"enhancement","subproject":"cie-ideaapp","project":"cie"},{"created_at":"2017-12-20T11:02:59Z","url":"https://github.com/italia/cie-ideaapp/issues/9","title":"Allargare campo con numero carta","name":"cie-ideaapp","language":["java","android"],"repository_url":"https://github.com/italia/cie-ideaapp","labels":["enhancement"],"type":"enhancement","subproject":"cie-ideaapp","project":"cie"},{"created_at":"2017-12-20T11:01:31Z","url":"https://github.com/italia/cie-ideaapp/issues/8","title":"Migliorare il formato delle date","name":"cie-ideaapp","language":["java","android"],"repository_url":"https://github.com/italia/cie-ideaapp","labels":["enhancement"],"type":"enhancement","subproject":"cie-ideaapp","project":"cie"},{"created_at":"2017-09-28T17:45:41Z","url":"https://github.com/italia/cie-ideaapp/issues/1","title":"Testare/documentare/migliorare/ampliare l'app IDEA","name":"cie-ideaapp","language":["java","android"],"repository_url":"https://github.com/italia/cie-ideaapp","labels":["enhancement"],"type":"enhancement","subproject":"cie-ideaapp","project":"cie"},{"created_at":"2018-03-20T15:39:47Z","url":"https://github.com/italia/spid-metadata-builder/issues/8","title":"Tool di validazione metadati","name":"spid-metadata-builder","language":[],"repository_url":"https://github.com/italia/spid-metadata-builder","labels":[],"type":"","subproject":"spid-metadata-builder","project":"spid"},{"created_at":"2017-09-15T14:16:23Z","url":"https://github.com/italia/designers.italia.it/issues/48","title":"Nuovo stile designers.italia.it","name":"designers.italia.it","language":[],"repository_url":"https://github.com/italia/designers.italia.it","labels":["bug"],"type":"bug","subproject":"designers.italia.it","project":"website"},{"created_at":"2017-09-24T16:46:53Z","url":"https://github.com/italia/spid-wordpress/issues/9","title":"Completamento plugin WordPress","name":"spid-wordpress","language":["php","wordpress"],"repository_url":"https://github.com/italia/spid-wordpress","labels":["enhancement","question"],"type":"enhancement","subproject":"spid-wordpress","project":"spid"},{"created_at":"2019-08-27T13:09:00Z","url":"https://github.com/italia/ckan-it/issues/44","title":"Attivazione datastore","name":"ckan-it","language":["docker"],"repository_url":"https://github.com/italia/ckan-it","labels":["enhancement"],"type":"Hacktoberfest","subproject":"ckan-it","project":"other"},{"created_at":"2017-10-03T11:35:37Z","url":"https://github.com/italia/daf-ontologie-vocabolari-controllati/issues/2","title":"Enhancing ontology alignments","name":"daf-ontologie-vocabolari-controllati","language":[],"repository_url":"https://github.com/italia/daf-ontologie-vocabolari-controllati","labels":["enhancement"],"type":"enhancement","subproject":"daf-ontologie-vocabolari-controllati","project":"daf"},{"created_at":"2017-10-03T11:33:05Z","url":"https://github.com/italia/daf-ontologie-vocabolari-controllati/issues/1","title":"Extending OntoPiA","name":"daf-ontologie-vocabolari-controllati","language":[],"repository_url":"https://github.com/italia/daf-ontologie-vocabolari-controllati","labels":["enhancement"],"type":"enhancement","subproject":"daf-ontologie-vocabolari-controllati","project":"daf"},{"created_at":"2019-03-25T16:48:15Z","url":"https://github.com/italia/daf-dataportal/issues/446","title":"Create a React component to view a CSV as a table (from old daf-dataportal-public repo)","name":"daf-dataportal","language":["react","docker"],"repository_url":"https://github.com/italia/daf-dataportal","labels":["enhancement"],"type":"enhancement","subproject":"daf-dataportal","project":"daf"},{"created_at":"2019-03-25T16:44:51Z","url":"https://github.com/italia/daf-dataportal/issues/445","title":"Implement SPID Login (from old daf-dataportal-public repo)","name":"daf-dataportal","language":["react","docker"],"repository_url":"https://github.com/italia/daf-dataportal","labels":["enhancement"],"type":"enhancement","subproject":"daf-dataportal","project":"daf"},{"created_at":"2019-03-25T16:41:33Z","url":"https://github.com/italia/daf-dataportal/issues/444","title":"Create a \"map\" React component (from old daf-dataportal-public repo)","name":"daf-dataportal","language":["react","docker"],"repository_url":"https://github.com/italia/daf-dataportal","labels":["enhancement"],"type":"enhancement","subproject":"daf-dataportal","project":"daf"},{"created_at":"2019-03-25T16:36:14Z","url":"https://github.com/italia/daf-dataportal/issues/443","title":"DataStory: add link from image to dashboard (from old daf-dataportal-public repo)","name":"daf-dataportal","language":["react","docker"],"repository_url":"https://github.com/italia/daf-dataportal","labels":["enhancement"],"type":"enhancement","subproject":"daf-dataportal","project":"daf"},{"created_at":"2018-01-31T20:57:18Z","url":"https://github.com/italia/daf-dataportal/issues/130","title":"Add description for the \"Licenza\" field","name":"daf-dataportal","language":["react","docker"],"repository_url":"https://github.com/italia/daf-dataportal","labels":[],"type":"","subproject":"daf-dataportal","project":"daf"},{"created_at":"2017-09-25T09:42:00Z","url":"https://github.com/italia/daf-dataportal/issues/50","title":"Create a showcase dashboard to visualize useful data","name":"daf-dataportal","language":["react","docker"],"repository_url":"https://github.com/italia/daf-dataportal","labels":["new project"],"type":"new project","subproject":"daf-dataportal","project":"daf"},{"created_at":"2017-09-21T16:49:01Z","url":"https://github.com/italia/daf-dataportal/issues/48","title":"Create an Apache Superset theme","name":"daf-dataportal","language":["react","docker"],"repository_url":"https://github.com/italia/daf-dataportal","labels":["new project"],"type":"new project","subproject":"daf-dataportal","project":"daf"},{"created_at":"2017-09-21T16:47:12Z","url":"https://github.com/italia/daf-dataportal/issues/47","title":"Adapt the metabase theme so it follows the guidelines","name":"daf-dataportal","language":["react","docker"],"repository_url":"https://github.com/italia/daf-dataportal","labels":[],"type":"","subproject":"daf-dataportal","project":"daf"},{"created_at":"2017-09-21T16:43:43Z","url":"https://github.com/italia/daf-dataportal/issues/46","title":"Create a microservice to cache Metabase plots","name":"daf-dataportal","language":["react","docker"],"repository_url":"https://github.com/italia/daf-dataportal","labels":["enhancement"],"type":"enhancement","subproject":"daf-dataportal","project":"daf"},{"created_at":"2017-09-21T16:40:20Z","url":"https://github.com/italia/daf-dataportal/issues/45","title":"Create a \"Medium\"-style editor for stories","name":"daf-dataportal","language":["react","docker"],"repository_url":"https://github.com/italia/daf-dataportal","labels":["enhancement"],"type":"enhancement","subproject":"daf-dataportal","project":"daf"},{"created_at":"2017-09-21T16:27:01Z","url":"https://github.com/italia/daf-dataportal/issues/44","title":"Port DataPortal's design to the Style Guide","name":"daf-dataportal","language":["react","docker"],"repository_url":"https://github.com/italia/daf-dataportal","labels":["enhancement"],"type":"enhancement","subproject":"daf-dataportal","project":"daf"},{"created_at":"2017-09-21T16:24:31Z","url":"https://github.com/italia/daf-dataportal/issues/43","title":"Create an API endpoint to save data on PostgreSQL","name":"daf-dataportal","language":["react","docker"],"repository_url":"https://github.com/italia/daf-dataportal","labels":["enhancement"],"type":"enhancement","subproject":"daf-dataportal","project":"daf"},{"created_at":"2017-09-21T16:22:44Z","url":"https://github.com/italia/daf-dataportal/issues/42","title":"Create ansible recipes to ease deployment on the cloud","name":"daf-dataportal","language":["react","docker"],"repository_url":"https://github.com/italia/daf-dataportal","labels":["enhancement"],"type":"enhancement","subproject":"daf-dataportal","project":"daf"},{"created_at":"2017-10-03T12:36:37Z","url":"https://github.com/italia/daf-semantics/issues/5","title":"Comments/Proposals on prototype semantic-frontend","name":"daf-semantics","language":[],"repository_url":"https://github.com/italia/daf-semantics","labels":["new project"],"type":"new project","subproject":"daf-semantics","project":"daf"},{"created_at":"2017-09-26T19:09:07Z","url":"https://github.com/italia/security-pulse/issues/2","title":"Aggiunta visualizzazione dati email a dashboard Pulse","name":"security-pulse","language":["frontend"],"repository_url":"https://github.com/italia/security-pulse","labels":["enhancement"],"type":"enhancement","subproject":"security-pulse","project":"security"},{"created_at":"2017-09-26T19:08:44Z","url":"https://github.com/italia/security-pulse/issues/1","title":"Cambio frontend di Pulse secondo linee guida","name":"security-pulse","language":["frontend"],"repository_url":"https://github.com/italia/security-pulse","labels":[],"type":"","subproject":"security-pulse","project":"security"},{"created_at":"2017-09-26T19:07:55Z","url":"https://github.com/italia/security-securethenews/issues/1","title":"Aggiunta colonne a Securethenews","name":"security-securethenews","language":["frontend"],"repository_url":"https://github.com/italia/security-securethenews","labels":["enhancement"],"type":"enhancement","subproject":"security-securethenews","project":"security"},{"created_at":"2017-09-26T10:35:25Z","url":"https://github.com/italia/spid-perl-mojolicious/issues/1","title":"Sviluppo plugin per autenticazione SPID con Mojolicious","name":"spid-perl-mojolicious","language":[],"repository_url":"https://github.com/italia/spid-perl-mojolicious","labels":["new project"],"type":"new project","subproject":"spid-perl-mojolicious","project":"spid"},{"created_at":"2019-08-07T09:58:13Z","url":"https://github.com/italia/bootstrap-italia/issues/376","title":"Dismissione di OwlCarousel in favore di una libreria più moderna","name":"bootstrap-italia","language":["design","frontend"],"repository_url":"https://github.com/italia/bootstrap-italia","labels":["accessibility"],"type":"Hacktoberfest","subproject":"bootstrap-italia","project":"other"},{"created_at":"2019-05-27T07:06:58Z","url":"https://github.com/italia/bootstrap-italia/issues/326","title":"Pubblicare Bootstrap-Italia come WebJars","name":"bootstrap-italia","language":["design","frontend"],"repository_url":"https://github.com/italia/bootstrap-italia","labels":[],"type":"Hacktoberfest","subproject":"bootstrap-italia","project":"other"},{"created_at":"2019-02-01T17:17:14Z","url":"https://github.com/italia/bootstrap-italia/issues/275","title":"ReferenceError: bootstrap is not defined","name":"bootstrap-italia","language":["design","frontend"],"repository_url":"https://github.com/italia/bootstrap-italia","labels":["bug"],"type":"Hacktoberfest","subproject":"bootstrap-italia","project":"other"},{"created_at":"2018-12-27T15:55:29Z","url":"https://github.com/italia/bootstrap-italia/issues/258","title":"Dropdown non funzionante con la versione 6.1.5 di Angular.","name":"bootstrap-italia","language":["design","frontend"],"repository_url":"https://github.com/italia/bootstrap-italia","labels":["bug"],"type":"Hacktoberfest","subproject":"bootstrap-italia","project":"other"},{"created_at":"2018-07-30T08:01:06Z","url":"https://github.com/italia/bootstrap-italia/issues/159","title":"Area Contenuti: Tabelle","name":"bootstrap-italia","language":["design","frontend"],"repository_url":"https://github.com/italia/bootstrap-italia","labels":[],"type":"Hacktoberfest","subproject":"bootstrap-italia","project":"other"},{"created_at":"2019-09-30T07:28:53Z","url":"https://github.com/italia/design-react-kit/issues/363","title":"[FEATURE] Megamenu component","name":"design-react-kit","language":["react","design"],"repository_url":"https://github.com/italia/design-react-kit","labels":["enhancement"],"type":"enhancement","subproject":"design-react-kit","project":"design"},{"created_at":"2017-09-26T14:02:33Z","url":"https://github.com/italia/design-angular/issues/1","title":"Implement/prototype a new framework that implements the design guidelines","name":"design-angular","language":["angular","design"],"repository_url":"https://github.com/italia/design-angular","labels":["new project"],"type":"new project","subproject":"design-angular","project":"design"},{"created_at":"2017-10-04T11:19:23Z","url":"https://github.com/italia/cie-mrtd-dotnet-sdk/issues/4","title":"Develop demo application for reading and displaying card contents","name":"cie-mrtd-dotnet-sdk","language":["csharp"],"repository_url":"https://github.com/italia/cie-mrtd-dotnet-sdk","labels":["new project"],"type":"new project","subproject":"cie-mrtd-dotnet-sdk","project":"cie"},{"created_at":"2019-02-05T14:53:13Z","url":"https://github.com/italia/design-joomla-theme/issues/2","title":"Create a Joomla theme that implements the Italia Design Guidelines","name":"design-joomla-theme","language":["design","joomla"],"repository_url":"https://github.com/italia/design-joomla-theme","labels":["gsoc ideas","new project"],"type":"new project","subproject":"design-joomla-theme","project":"design"},{"created_at":"2019-02-05T14:51:16Z","url":"https://github.com/italia/design-drupal-theme/issues/2","title":"Create a Drupal theme that implements the Italia Design Guidelines","name":"design-drupal-theme","language":["design"],"repository_url":"https://github.com/italia/design-drupal-theme","labels":["gsoc ideas","new project"],"type":"new project","subproject":"design-drupal-theme","project":"design"},{"created_at":"2017-09-26T19:06:32Z","url":"https://github.com/italia/security-dashboard/issues/1","title":"Crea una dashboard per lo stato dell'adozione delle pratiche web sicure","name":"security-dashboard","language":["html","frontend"],"repository_url":"https://github.com/italia/security-dashboard","labels":["new project"],"type":"new project","subproject":"security-dashboard","project":"security"},{"created_at":"2017-10-07T10:40:01Z","url":"https://github.com/italia/security-recipes/issues/2","title":"Gestione del deploy di un sistema di notifiche legato al sistema di scan","name":"security-recipes","language":["docker"],"repository_url":"https://github.com/italia/security-recipes","labels":["new project"],"type":"new project","subproject":"security-recipes","project":"security"},{"created_at":"2017-09-26T21:37:37Z","url":"https://github.com/italia/security-recipes/issues/1","title":"Gestione del deploy di un sistema di scanning agganciato a pulse","name":"security-recipes","language":["docker"],"repository_url":"https://github.com/italia/security-recipes","labels":["new project"],"type":"new project","subproject":"security-recipes","project":"security"},{"created_at":"2017-10-03T10:34:30Z","url":"https://github.com/italia/spid-magento/issues/1","title":"Sviluppo di un'estensione per autenticazione SPID in Magento","name":"spid-magento","language":["php","magento"],"repository_url":"https://github.com/italia/spid-magento","labels":["new project"],"type":"new project","subproject":"spid-magento","project":"spid"},{"created_at":"2017-10-04T12:41:07Z","url":"https://github.com/italia/cie-nis-python-sdk/issues/2","title":"Develop a library for reading the NIS code with PKCS#11","name":"cie-nis-python-sdk","language":[],"repository_url":"https://github.com/italia/cie-nis-python-sdk","labels":["new project"],"type":"new project","subproject":"cie-nis-python-sdk","project":"cie"},{"created_at":"2017-10-05T14:34:02Z","url":"https://github.com/italia/spid-limesurvey-plugin/issues/1","title":"Sviluppo di un'estensione per autenticazione SPID in LimeSurvey","name":"spid-limesurvey-plugin","language":["php"],"repository_url":"https://github.com/italia/spid-limesurvey-plugin","labels":["new project"],"type":"new project","subproject":"spid-limesurvey-plugin","project":"spid"},{"created_at":"2017-10-06T19:35:25Z","url":"https://github.com/italia/spid-joomla-plugin/issues/1","title":"Sviluppo plugin per autenticazione SPID su Joomla","name":"spid-joomla-plugin","language":["php","joomla"],"repository_url":"https://github.com/italia/spid-joomla-plugin","labels":["new project"],"type":"new project","subproject":"spid-joomla-plugin","project":"spid"},{"created_at":"2017-10-07T08:06:38Z","url":"https://github.com/italia/design-qml-components/issues/1","title":"Create a set of QML components based on the User Interface design guidelines.","name":"design-qml-components","language":["design","frontend"],"repository_url":"https://github.com/italia/design-qml-components","labels":["new project"],"type":"new project","subproject":"design-qml-components","project":"design"},{"created_at":"2017-10-07T10:21:02Z","url":"https://github.com/italia/18app-cpp-sdk/issues/1","title":"Write a C++ SDK for merchants","name":"18app-cpp-sdk","language":["cpp"],"repository_url":"https://github.com/italia/18app-cpp-sdk","labels":[],"type":"","subproject":"18app-cpp-sdk","project":"18app"},{"created_at":"2017-10-07T14:52:13Z","url":"https://github.com/italia/spid-liferay/issues/1","title":"Sviluppo plugin per autenticazione Liferay con SPID","name":"spid-liferay","language":[],"repository_url":"https://github.com/italia/spid-liferay","labels":["new project"],"type":"new project","subproject":"spid-liferay","project":"spid"},{"created_at":"2017-10-07T14:57:35Z","url":"https://github.com/italia/18app-python-sdk/issues/1","title":"Write a Python SDK for merchants","name":"18app-python-sdk","language":[],"repository_url":"https://github.com/italia/18app-python-sdk","labels":["new project"],"type":"new project","subproject":"18app-python-sdk","project":"18app"},{"created_at":"2017-10-08T08:15:24Z","url":"https://github.com/italia/spid-ionic-sdk/issues/1","title":"Sviluppo di una libreria per autenticazione SPID in app basate su Ionic","name":"spid-ionic-sdk","language":[],"repository_url":"https://github.com/italia/spid-ionic-sdk","labels":["new project"],"type":"new project","subproject":"spid-ionic-sdk","project":"spid"},{"created_at":"2017-11-23T17:32:13Z","url":"https://github.com/italia/cie-nis-java-sdk/issues/3","title":"Create a Java SDK for the electronic ID card (CIE)","name":"cie-nis-java-sdk","language":[],"repository_url":"https://github.com/italia/cie-nis-java-sdk","labels":["enhancement","gsoc ideas"],"type":"enhancement","subproject":"cie-nis-java-sdk","project":"cie"},{"created_at":"2017-11-23T17:31:20Z","url":"https://github.com/italia/cie-nis-java-sdk/issues/2","title":"PKCS#11 support","name":"cie-nis-java-sdk","language":[],"repository_url":"https://github.com/italia/cie-nis-java-sdk","labels":["enhancement"],"type":"enhancement","subproject":"cie-nis-java-sdk","project":"cie"},{"created_at":"2018-04-18T20:23:14Z","url":"https://github.com/italia/cie-nis-cpp-sdk/issues/45","title":"C++ API should be improved by managing exceptions on error condition","name":"cie-nis-cpp-sdk","language":[],"repository_url":"https://github.com/italia/cie-nis-cpp-sdk","labels":["good first issue"],"type":"","subproject":"cie-nis-cpp-sdk","project":"cie"},{"created_at":"2018-04-18T19:51:43Z","url":"https://github.com/italia/cie-nis-cpp-sdk/issues/44","title":"Fix heterogeneous typedefs on POD types","name":"cie-nis-cpp-sdk","language":[],"repository_url":"https://github.com/italia/cie-nis-cpp-sdk","labels":["good first issue"],"type":"","subproject":"cie-nis-cpp-sdk","project":"cie"},{"created_at":"2018-04-18T19:47:05Z","url":"https://github.com/italia/cie-nis-cpp-sdk/issues/43","title":"Improve log system","name":"cie-nis-cpp-sdk","language":[],"repository_url":"https://github.com/italia/cie-nis-cpp-sdk","labels":["good first issue"],"type":"","subproject":"cie-nis-cpp-sdk","project":"cie"},{"created_at":"2018-04-14T14:00:01Z","url":"https://github.com/italia/cie-nis-cpp-sdk/issues/39","title":"Avoid reading Elementary File beyond the EOF","name":"cie-nis-cpp-sdk","language":[],"repository_url":"https://github.com/italia/cie-nis-cpp-sdk","labels":[],"type":"","subproject":"cie-nis-cpp-sdk","project":"cie"},{"created_at":"2018-04-14T13:13:36Z","url":"https://github.com/italia/cie-nis-cpp-sdk/issues/38","title":"Coding style improvement: replace nested-ifs with exception management","name":"cie-nis-cpp-sdk","language":[],"repository_url":"https://github.com/italia/cie-nis-cpp-sdk","labels":["good first issue"],"type":"","subproject":"cie-nis-cpp-sdk","project":"cie"},{"created_at":"2018-04-14T13:11:35Z","url":"https://github.com/italia/cie-nis-cpp-sdk/issues/37","title":"Get rid of Byte{Dyn}Array in favour of vector<byte>","name":"cie-nis-cpp-sdk","language":[],"repository_url":"https://github.com/italia/cie-nis-cpp-sdk","labels":["good first issue"],"type":"","subproject":"cie-nis-cpp-sdk","project":"cie"},{"created_at":"2018-03-29T20:26:24Z","url":"https://github.com/italia/cie-nis-cpp-sdk/issues/30","title":"Link test samples with static lib","name":"cie-nis-cpp-sdk","language":[],"repository_url":"https://github.com/italia/cie-nis-cpp-sdk","labels":["good first issue"],"type":"","subproject":"cie-nis-cpp-sdk","project":"cie"},{"created_at":"2018-03-29T19:33:47Z","url":"https://github.com/italia/cie-nis-cpp-sdk/issues/29","title":"Modify NIS polling to be triggered on card status changes","name":"cie-nis-cpp-sdk","language":[],"repository_url":"https://github.com/italia/cie-nis-cpp-sdk","labels":["enhancement","good first issue"],"type":"enhancement","subproject":"cie-nis-cpp-sdk","project":"cie"},{"created_at":"2018-03-22T12:20:36Z","url":"https://github.com/italia/cie-nis-cpp-sdk/issues/26","title":"Modify test example to accept token not immediately present before connecting","name":"cie-nis-cpp-sdk","language":[],"repository_url":"https://github.com/italia/cie-nis-cpp-sdk","labels":["enhancement","good first issue"],"type":"enhancement","subproject":"cie-nis-cpp-sdk","project":"cie"},{"created_at":"2018-03-22T12:16:53Z","url":"https://github.com/italia/cie-nis-cpp-sdk/issues/25","title":"Beautify documentation - use cases","name":"cie-nis-cpp-sdk","language":[],"repository_url":"https://github.com/italia/cie-nis-cpp-sdk","labels":["enhancement","good first issue"],"type":"enhancement","subproject":"cie-nis-cpp-sdk","project":"cie"},{"created_at":"2018-03-22T12:16:01Z","url":"https://github.com/italia/cie-nis-cpp-sdk/issues/24","title":"Beautify documentation - homepage","name":"cie-nis-cpp-sdk","language":[],"repository_url":"https://github.com/italia/cie-nis-cpp-sdk","labels":["enhancement","good first issue"],"type":"enhancement","subproject":"cie-nis-cpp-sdk","project":"cie"},{"created_at":"2017-11-23T17:18:48Z","url":"https://github.com/italia/cie-nis-cpp-sdk/issues/4","title":"PKCS#11 support","name":"cie-nis-cpp-sdk","language":[],"repository_url":"https://github.com/italia/cie-nis-cpp-sdk","labels":["enhancement"],"type":"enhancement","subproject":"cie-nis-cpp-sdk","project":"cie"},{"created_at":"2017-11-23T17:18:04Z","url":"https://github.com/italia/cie-nis-cpp-sdk/issues/3","title":"Linux support","name":"cie-nis-cpp-sdk","language":[],"repository_url":"https://github.com/italia/cie-nis-cpp-sdk","labels":["enhancement"],"type":"enhancement","subproject":"cie-nis-cpp-sdk","project":"cie"},{"created_at":"2017-11-23T17:17:42Z","url":"https://github.com/italia/cie-nis-cpp-sdk/issues/2","title":"MacOS X support","name":"cie-nis-cpp-sdk","language":[],"repository_url":"https://github.com/italia/cie-nis-cpp-sdk","labels":["enhancement"],"type":"enhancement","subproject":"cie-nis-cpp-sdk","project":"cie"},{"created_at":"2017-11-23T17:34:34Z","url":"https://github.com/italia/cie-nis-objc-sdk/issues/2","title":"PKCS#11 support","name":"cie-nis-objc-sdk","language":[],"repository_url":"https://github.com/italia/cie-nis-objc-sdk","labels":["enhancement"],"type":"enhancement","subproject":"cie-nis-objc-sdk","project":"cie"},{"created_at":"2017-11-23T17:34:09Z","url":"https://github.com/italia/cie-nis-objc-sdk/issues/1","title":"Turn this into a (documented) library","name":"cie-nis-objc-sdk","language":[],"repository_url":"https://github.com/italia/cie-nis-objc-sdk","labels":["enhancement"],"type":"enhancement","subproject":"cie-nis-objc-sdk","project":"cie"},{"created_at":"2019-08-21T07:56:44Z","url":"https://github.com/italia/docs.italia.it/issues/258","title":"Validazione RST","name":"docs.italia.it","language":[],"repository_url":"https://github.com/italia/docs.italia.it","labels":[],"type":"","subproject":"docs.italia.it","project":"website"},{"created_at":"2019-02-13T17:13:45Z","url":"https://github.com/italia/developers-italia-backend/issues/79","title":"Improve CLI","name":"developers-italia-backend","language":[],"repository_url":"https://github.com/italia/developers-italia-backend","labels":["enhancement"],"type":"Hacktoberfest","subproject":"developers-italia-backend","project":"other"},{"created_at":"2020-07-09T10:13:27Z","url":"https://github.com/italia/publiccode-parser-go/issues/40","title":"Gitlab sometime adds a dash in raw url","name":"publiccode-parser-go","language":[],"repository_url":"https://github.com/italia/publiccode-parser-go","labels":["bug"],"type":"bug","subproject":"publiccode-parser-go","project":"other"},{"created_at":"2019-10-14T15:17:07Z","url":"https://github.com/italia/publiccode-parser-go/issues/19","title":"When some keys are in error, mandatory key are not enforced","name":"publiccode-parser-go","language":[],"repository_url":"https://github.com/italia/publiccode-parser-go","labels":["bug"],"type":"bug","subproject":"publiccode-parser-go","project":"other"},{"created_at":"2019-07-29T14:17:05Z","url":"https://github.com/italia/publiccode-parser-go/issues/11","title":"Panic not managed when sub key is null","name":"publiccode-parser-go","language":[],"repository_url":"https://github.com/italia/publiccode-parser-go","labels":["bug"],"type":"bug","subproject":"publiccode-parser-go","project":"other"},{"created_at":"2019-05-08T17:10:27Z","url":"https://github.com/italia/publiccode-parser-go/issues/10","title":"Exception not catched","name":"publiccode-parser-go","language":[],"repository_url":"https://github.com/italia/publiccode-parser-go","labels":["bug"],"type":"bug","subproject":"publiccode-parser-go","project":"other"},{"created_at":"2020-03-16T10:25:28Z","url":"https://github.com/italia/developers-italia-onboarding/issues/100","title":"Menu in footer might be confusing","name":"developers-italia-onboarding","language":[],"repository_url":"https://github.com/italia/developers-italia-onboarding","labels":["enhancement"],"type":"enhancement","subproject":"developers-italia-onboarding","project":"other"},{"created_at":"2019-02-13T17:37:04Z","url":"https://github.com/italia/publiccode.yml/issues/36","title":"Naming issue \"public administration\"","name":"publiccode.yml","language":[],"repository_url":"https://github.com/italia/publiccode.yml","labels":["enhancement","question"],"type":"enhancement","subproject":"publiccode.yml","project":"other"},{"created_at":"2018-10-28T10:43:16Z","url":"https://github.com/italia/fatturapa-testsdi/issues/43","title":"implement MTOM SOAP (multipart MIME)","name":"fatturapa-testsdi","language":[],"repository_url":"https://github.com/italia/fatturapa-testsdi","labels":[],"type":"","subproject":"fatturapa-testsdi","project":"other"},{"created_at":"2018-10-25T08:31:59Z","url":"https://github.com/italia/fatturapa-testsdi/issues/40","title":"Composer install error","name":"fatturapa-testsdi","language":[],"repository_url":"https://github.com/italia/fatturapa-testsdi","labels":[],"type":"","subproject":"fatturapa-testsdi","project":"other"},{"created_at":"2018-10-02T21:19:20Z","url":"https://github.com/italia/fatturapa-testsdi/issues/21","title":"signing","name":"fatturapa-testsdi","language":[],"repository_url":"https://github.com/italia/fatturapa-testsdi","labels":[],"type":"","subproject":"fatturapa-testsdi","project":"other"},{"created_at":"2018-09-12T13:08:51Z","url":"https://github.com/italia/fatturapa-testsdi/issues/12","title":"add DB constraints for status column in invoices table","name":"fatturapa-testsdi","language":[],"repository_url":"https://github.com/italia/fatturapa-testsdi","labels":["good first issue"],"type":"","subproject":"fatturapa-testsdi","project":"other"},{"created_at":"2019-02-08T14:24:45Z","url":"https://github.com/italia/publiccode-editor/issues/26","title":"Translation in Italian","name":"publiccode-editor","language":[],"repository_url":"https://github.com/italia/publiccode-editor","labels":["enhancement"],"type":"Hacktoberfest","subproject":"publiccode-editor","project":"other"},{"created_at":"2019-03-07T10:11:53Z","url":"https://github.com/italia/daf-community/issues/1","title":"Fare il setup delle attività ","name":"daf-community","language":[],"repository_url":"https://github.com/italia/daf-community","labels":[],"type":"","subproject":"daf-community","project":"daf"},{"created_at":"2019-11-14T11:04:49Z","url":"https://github.com/italia/ckanext-dcatapit/issues/4","title":"Add controlled vocabularies of provinces and cities for organizations","name":"ckanext-dcatapit","language":["docker"],"repository_url":"https://github.com/italia/ckanext-dcatapit","labels":["enhancement"],"type":"enhancement","subproject":"ckanext-dcatapit","project":"other"},{"created_at":"2020-06-05T13:58:19Z","url":"https://github.com/italia/publiccode-validator/issues/9","title":"Wrong validation error whether an invalid yml file is submitted","name":"publiccode-validator","language":[],"repository_url":"https://github.com/italia/publiccode-validator","labels":["bug"],"type":"bug","subproject":"publiccode-validator","project":"other"},{"created_at":"2019-10-25T09:08:14Z","url":"https://github.com/italia/public-opendata-sources/issues/12","title":"Add contact informations to sources","name":"public-opendata-sources","language":[],"repository_url":"https://github.com/italia/public-opendata-sources","labels":["enhancement","good first issue"],"type":"enhancement","subproject":"public-opendata-sources","project":"other"},{"created_at":"2019-10-23T14:06:01Z","url":"https://github.com/italia/public-opendata-sources/issues/11","title":"[REPORT] Comune di Reggio Calabria","name":"public-opendata-sources","language":[],"repository_url":"https://github.com/italia/public-opendata-sources","labels":["bug"],"type":"bug","subproject":"public-opendata-sources","project":"other"},{"created_at":"2019-10-23T13:58:17Z","url":"https://github.com/italia/public-opendata-sources/issues/10","title":"[REPORT] Città Metropolitana di Roma Capitale","name":"public-opendata-sources","language":[],"repository_url":"https://github.com/italia/public-opendata-sources","labels":["bug"],"type":"bug","subproject":"public-opendata-sources","project":"other"},{"created_at":"2019-10-23T13:34:20Z","url":"https://github.com/italia/public-opendata-sources/issues/8","title":"Italian documentation","name":"public-opendata-sources","language":[],"repository_url":"https://github.com/italia/public-opendata-sources","labels":["documentation","good first issue"],"type":"","subproject":"public-opendata-sources","project":"other"},{"created_at":"2019-10-17T16:17:45Z","url":"https://github.com/italia/public-opendata-sources/issues/3","title":"[REPORT] Regione Veneto","name":"public-opendata-sources","language":[],"repository_url":"https://github.com/italia/public-opendata-sources","labels":["bug"],"type":"bug","subproject":"public-opendata-sources","project":"other"}]